odoo/addons/product_catalog_sale/README.rst
odoo/addons/product_catalog_sale/__init__.py
odoo/addons/product_catalog_sale/__manifest__.py
odoo/addons/product_catalog_sale/i18n/it.po
odoo/addons/product_catalog_sale/i18n/product_catalog_sale.pot
odoo/addons/product_catalog_sale/models/__init__.py
odoo/addons/product_catalog_sale/models/sale_order.py
odoo/addons/product_catalog_sale/readme/CONTRIBUTORS.md
odoo/addons/product_catalog_sale/readme/DESCRIPTION.md
odoo/addons/product_catalog_sale/readme/ROADMAP.md
odoo/addons/product_catalog_sale/readme/USAGE.md
odoo/addons/product_catalog_sale/static/description/icon.png
odoo/addons/product_catalog_sale/static/description/index.html
odoo/addons/product_catalog_sale/views/sale_order_views.xml
odoo_addon_product_catalog_sale-16.0.1.0.0.4.dist-info/METADATA
odoo_addon_product_catalog_sale-16.0.1.0.0.4.dist-info/WHEEL
odoo_addon_product_catalog_sale-16.0.1.0.0.4.dist-info/top_level.txt
odoo_addon_product_catalog_sale-16.0.1.0.0.4.dist-info/RECORD
