Metadata-Version: 2.1
Name: odoo-addon-product_catalog_sale
Version: 16.0.1.0.0.4
Summary: Backport of Odoos v17 product catalog for sale orders
Home-page: https://github.com/OCA/product-attribute
Author: Odoo SA, Tecnativa, Odoo Community Association (OCA)
Author-email: support@odoo-community.org
License: AGPL-3
Classifier: Programming Language :: Python
Classifier: Framework :: Odoo
Classifier: Framework :: Odoo :: 16.0
Classifier: License :: OSI Approved :: GNU Affero General Public License v3
Requires-Python: >=3.10
Requires-Dist: odoo-addon-product-catalog<16.1dev,>=16.0dev
Requires-Dist: odoo<16.1dev,>=16.0a
